{"title":"Combined feed","url":"https://Vinnl.github.io/feeds/all.xml","elements":[{"title":"Johann Adam von Questenberg (Wikipedia — did you know?)","contents":"... that <b><a href=\"/wiki/Johann_Adam_von_Questenberg\" title=\"Johann Adam von Questenberg\">Johann Adam von Questenberg</a></b> <i>(pictured)</i>, who worked for the <a href=\"/wiki/Emperor_of_Austria#The_Imperial_Court\" title=\"Emperor of Austria\">Austrian Imperial Court</a>, was an amateur <a href=\"/wiki/Lute\" title=\"Lute\">lutenist</a> who made his palace a music centre?","link":"https://en.wikipedia.org/wiki/Johann_Adam_von_Questenberg","retrieved":1634319802738},{"title":"Questprobe featuring The Hulk (Wikipedia — did you know?)","contents":"... that the <a href=\"/wiki/Chief_Examiner\" title=\"Chief Examiner\">Chief Examiner</a>, who first appeared in <i><b><a href=\"/wiki/Questprobe_featuring_The_Hulk\" title=\"Questprobe featuring The Hulk\">Questprobe featuring The Hulk</a></b></i>, was modeled after game designer <a href=\"/wiki/Scott_Adams_(game_designer)\" title=\"Scott Adams (game designer)\">Scott Adams</a>?","link":"https://en.wikipedia.org/wiki/Questprobe_featuring_The_Hulk","retrieved":1634319802738},{"title":"his sculptures for the Daily Mirror (Wikipedia — did you know?)","contents":"... that in <b><a href=\"/wiki/Ben_Enwonwu%27s_Daily_Mirror_sculptures\" title=\"Ben Enwonwu's Daily Mirror sculptures\">his sculptures for the <i>Daily Mirror</i></a></b>, <a href=\"/wiki/Ben_Enwonwu\" title=\"Ben Enwonwu\">Ben Enwonwu</a> carved a \"religious group\" flying news all over the world?","link":"https://en.wikipedia.org/wiki/Ben_Enwonwu%27s_Daily_Mirror_sculptures","retrieved":1634319802738},{"title":"Eazy PC (Wikipedia — did you know?)","contents":"... that <a href=\"/wiki/Zenith_Data_Systems\" title=\"Zenith Data Systems\">Zenith</a> equipped the <a href=\"/wiki/Floppy_disk\" title=\"Floppy disk\">floppy</a>-only models of the <b><a href=\"/wiki/Zenith_Eazy_PC\" title=\"Zenith Eazy PC\">Eazy PC</a></b> with power supplies too weak to accommodate a hard drive?","link":"https://en.wikipedia.org/wiki/Zenith_Eazy_PC","retrieved":1634319802741},{"title":"Romeo Beckham (Wikipedia — did you know?)","contents":"... that after the footballer <b><a href=\"/wiki/Romeo_Beckham\" title=\"Romeo Beckham\">Romeo Beckham</a></b> was released by Arsenal, he trained in tennis before returning to football five years later?","link":"https://en.wikipedia.org/wiki/Romeo_Beckham","retrieved":1634319802742},{"title":"Düben collection (Wikipedia — did you know?)","contents":"... that the <b><a href=\"/wiki/D%C3%BCben_collection\" title=\"Düben collection\">Düben collection</a></b> contains the sole surviving copies of many works by <a href=\"/wiki/Dieterich_Buxtehude\" title=\"Dieterich Buxtehude\">Dieterich Buxtehude</a>?","link":"https://en.wikipedia.org/wiki/D%C3%BCben_collection","retrieved":1634319802743},{"title":"Montacuta substriata (Wikipedia — did you know?)","contents":"... that the tiny bivalve mollusc <i><b><a href=\"/wiki/Montacuta_substriata\" title=\"Montacuta substriata\">Montacuta substriata</a></b></i> attaches to the spines of the <b><a href=\"/wiki/Spatangus_purpureus\" title=\"Spatangus purpureus\">purple heart urchin</a></b>, where it resembles a grain of sand?","link":"https://en.wikipedia.org/wiki/Montacuta_substriata","retrieved":1634319802746},{"title":"Abdullah Aidit (Wikipedia — did you know?)","contents":"... that <b><a href=\"/wiki/Abdullah_Aidit\" title=\"Abdullah Aidit\">Abdullah Aidit</a></b> did not want <a href=\"/wiki/D._N._Aidit\" title=\"D. N. Aidit\">his son</a> to change his name, mainly because he did not want to deal with the administrative consequences?","link":"https://en.wikipedia.org/wiki/Abdullah_Aidit","retrieved":1634319802748},{"title":"Central Dongcheng (Wikivoyage recommendations)","contents":"<style data-mw-deduplicate=\"TemplateStyles:r3732050\">.mw-parser-output .mainpage-shadowbox{color:white;background:rgb(16,16,16);background:rgba(0,0,0,0.3);border-radius:4px}.mw-parser-output .mainpage-shadowbox h2,.mw-parser-output .mainpage-shadowbox h3{color:white;border:none;font-family:sans-serif;line-height:1.2em;margin:0;padding:0}.mw-parser-output .mainpage-shadowbox a{color:white;font-weight:bold}.mw-parser-output .banner-image{position:relative;max-width:1125px;height:auto;margin-bottom:.6em}.mw-parser-output .banner-image img{max-width:100%;height:auto}.mw-parser-output .banner-box-wide{width:80%}.mw-parser-output .banner-box-left,.mw-parser-output .banner-box-right{padding:8px 7px;background:rgb(16,16,16);background:rgba(0,0,0,0.3);border-radius:4px;width:40%}.mw-parser-output .banner-box-left{text-align:left}.mw-parser-output .banner-box-right{text-align:right}.mw-parser-output .banner-box-2{position:absolute;z-index:2;min-width:20em}@media screen and (min-width:720px){.mw-parser-output .banner-image img.nolink{display:none}.mw-parser-output .mainpage-shadowbox h2{font-size:190%}.mw-parser-output .mainpage-shadowbox h3{font-size:150%}.mw-parser-output .banner-image{overflow:hidden}.mw-parser-output .banner-box-left{left:3%}.mw-parser-output .banner-box-right{right:3%}.mw-parser-output .banner-box-2{margin-top:2em}.mw-parser-output .banner-box-2 .quote{font-size:80%;line-height:1.2em}}@media screen and (max-width:720px){.mw-parser-output .banner-image img:not(.nolink){display:none}.mw-parser-output .banner-image>.mainpage-shadowbox{width:inherit!important;min-height:100%;margin-left:-150%;margin-right:150%;opacity:0;background:black}.mw-parser-output .mainpage-shadowbox .quote>a:after{content:\"\\a Tap to learn more.\";white-space:pre}.mw-parser-output .jcarousel-item:hover .mainpage-shadowbox{margin:unset;opacity:1;transition:margin 0.5s;bottom:50%}.mw-parser-output .jcarousel-control-prev,.mw-parser-output .jcarousel-control-next{display:none}.mw-parser-output .interactiveIcon{position:absolute;opacity:0.4;height:75%!important;width:auto;bottom:0;right:0}}</style>\n<div class=\"banner-image js-proportonal-resize\" style=\"font-size: 117.222%;\">\n<p>\t<img alt=\"Interactive icon.svg\" src=\"//upload.wikimedia.org/wikipedia/commons/thumb/e/e6/Interactive_icon.svg/220px-Interactive_icon.svg.png\" decoding=\"async\" class=\"nolink interactiveIcon\" srcset=\"//upload.wikimedia.org/wikipedia/commons/thumb/e/e6/Interactive_icon.svg/330px-Interactive_icon.svg.png 1.5x, //upload.wikimedia.org/wikipedia/commons/thumb/e/e6/Interactive_icon.svg/440px-Interactive_icon.svg.png 2x\" data-file-width=\"133\" data-file-height=\"200\" width=\"220\" height=\"331\">\n</p>\n\t<div class=\"mainpage-shadowbox banner-box-2 banner-box-right\" style=\"width:40%\">\n\t\t<h2><span class=\"mw-headline\" id=\"Central_Dongcheng\"><a href=\"/wiki/Beijing/Central_Dongcheng\" title=\"Beijing/Central Dongcheng\">Central Dongcheng</a></span></h2>\n\t\t<h3><span class=\"mw-headline\" id=\"Destination_of_the_month\"><a href=\"/wiki/Previous_Destinations_of_the_month\" title=\"Previous Destinations of the month\">Destination of the month</a></span></h3>\n\t\t<div class=\"quote\"><a href=\"/wiki/Beijing/Central_Dongcheng\" title=\"Beijing/Central Dongcheng\">From Tiananmen Square to Wangfujing street, much that draws visitors to Beijing can be found in Dongcheng.</a></div>\n\t</div>\n<p>\t<img alt=\"Beijing/Central Dongcheng\" src=\"//upload.wikimedia.org/wikivoyage/en/thumb/0/04/DongchengBanner1.jpg/1700px-DongchengBanner1.jpg\" decoding=\"async\" title=\"Beijing/Central Dongcheng\" class=\"nolink\" srcset=\"//upload.wikimedia.org/wikivoyage/en/0/04/DongchengBanner1.jpg 1.5x\" data-file-width=\"1710\" data-file-height=\"570\" width=\"1700\" height=\"567\">\n</p>\n\t<a href=\"/wiki/Beijing/Central_Dongcheng\" title=\"Beijing/Central Dongcheng\"><img alt=\"Beijing/Central Dongcheng\" src=\"//upload.wikimedia.org/wikivoyage/en/thumb/0/04/DongchengBanner1.jpg/1700px-DongchengBanner1.jpg\" decoding=\"async\" srcset=\"//upload.wikimedia.org/wikivoyage/en/0/04/DongchengBanner1.jpg 1.5x\" data-file-width=\"1710\" data-file-height=\"570\" width=\"1700\" height=\"567\"></a></div>","link":"https://en.wikivoyage.org/wiki/Beijing/Central_Dongcheng","retrieved":1633110288997},{"title":"Chavín de Huántar (Wikivoyage recommendations)","contents":"<link rel=\"mw-deduplicated-inline-style\" href=\"mw-data:TemplateStyles:r3732050\">\n<div class=\"banner-image js-proportonal-resize\" style=\"font-size: 117.222%;\">\n<p>\t<img alt=\"Interactive icon.svg\" src=\"//upload.wikimedia.org/wikipedia/commons/thumb/e/e6/Interactive_icon.svg/220px-Interactive_icon.svg.png\" decoding=\"async\" class=\"nolink interactiveIcon\" srcset=\"//upload.wikimedia.org/wikipedia/commons/thumb/e/e6/Interactive_icon.svg/330px-Interactive_icon.svg.png 1.5x, //upload.wikimedia.org/wikipedia/commons/thumb/e/e6/Interactive_icon.svg/440px-Interactive_icon.svg.png 2x\" data-file-width=\"133\" data-file-height=\"200\" width=\"220\" height=\"331\">\n</p>\n\t<div class=\"mainpage-shadowbox banner-box-2 banner-box-right\" style=\"width:40%\">\n\t\t<h2><span id=\"Chav.C3.ADn_de_Hu.C3.A1ntar\"></span><span class=\"mw-headline\" id=\"Chavín_de_Huántar\"><a href=\"/wiki/Chav%C3%ADn_de_Hu%C3%A1ntar\" title=\"Chavín de Huántar\">Chavín de Huántar</a></span></h2>\n\t\t<h3><span class=\"mw-headline\" id=\"Off_the_Beaten_Path\"><a href=\"/wiki/Previous_Destinations_of_the_month\" title=\"Previous Destinations of the month\">Off the Beaten Path</a></span></h3>\n\t\t<div class=\"quote\"><a href=\"/wiki/Chav%C3%ADn_de_Hu%C3%A1ntar\" title=\"Chavín de Huántar\">Explore the ancient Chavín culture and the Andean cuisine and admire great views in this little town that millenia ago was an important ceremonial site.</a></div>\n\t</div>\n<p>\t<img alt=\"Chavín de Huántar\" src=\"//upload.wikimedia.org/wikipedia/commons/d/d2/Chav%C3%ADn_de_Hu%C3%A1ntar_main_page_banner.jpg\" decoding=\"async\" title=\"Chavín de Huántar\" class=\"nolink\" data-file-width=\"1700\" data-file-height=\"567\" width=\"1700\" height=\"567\">\n</p>\n\t<a href=\"/wiki/Chav%C3%ADn_de_Hu%C3%A1ntar\" title=\"Chavín de Huántar\"><img alt=\"Chavín de Huántar\" src=\"//upload.wikimedia.org/wikipedia/commons/d/d2/Chav%C3%ADn_de_Hu%C3%A1ntar_main_page_banner.jpg\" decoding=\"async\" data-file-width=\"1700\" data-file-height=\"567\" width=\"1700\" height=\"567\"></a></div>","link":"https://en.wikivoyage.org/wiki/Chav%C3%ADn_de_Hu%C3%A1ntar","retrieved":1633974361781},{"title":"Game of Thrones tourism (Wikivoyage recommendations)","contents":"<link rel=\"mw-deduplicated-inline-style\" href=\"mw-data:TemplateStyles:r3732050\">\n<div class=\"banner-image js-proportonal-resize\" style=\"font-size: 117.222%;\">\n<p>\t<img alt=\"Interactive icon.svg\" src=\"//upload.wikimedia.org/wikipedia/commons/thumb/e/e6/Interactive_icon.svg/220px-Interactive_icon.svg.png\" decoding=\"async\" class=\"nolink interactiveIcon\" srcset=\"//upload.wikimedia.org/wikipedia/commons/thumb/e/e6/Interactive_icon.svg/330px-Interactive_icon.svg.png 1.5x, //upload.wikimedia.org/wikipedia/commons/thumb/e/e6/Interactive_icon.svg/440px-Interactive_icon.svg.png 2x\" data-file-width=\"133\" data-file-height=\"200\" width=\"220\" height=\"331\">\n</p>\n\t<div class=\"mainpage-shadowbox banner-box-2 banner-box-left\" style=\"width:40%\">\n\t\t<h2><span class=\"mw-headline\" id=\"Game_of_Thrones_tourism\"><a href=\"/wiki/Game_of_Thrones_tourism\" title=\"Game of Thrones tourism\">Game of Thrones tourism</a></span></h2>\n\t\t<h3><span class=\"mw-headline\" id=\"Featured_Travel_Topic\"><a href=\"/wiki/Previous_Featured_Travel_Topics\" class=\"mw-redirect\" title=\"Previous Featured Travel Topics\">Featured Travel Topic</a></span></h3>\n\t\t<div class=\"quote\"><a href=\"/wiki/Game_of_Thrones_tourism\" title=\"Game of Thrones tourism\">An exceedingly popular TV series with more Emmy awards than any other. Much of it was shot on location in places that are interesting in their own right as well as to fans.</a></div>\n\t</div>\n<p>\t<img alt=\"Game of Thrones tourism\" src=\"//upload.wikimedia.org/wikivoyage/en/thumb/e/e9/GoTBanner1.jpg/1700px-GoTBanner1.jpg\" decoding=\"async\" title=\"Game of Thrones tourism\" class=\"nolink\" srcset=\"//upload.wikimedia.org/wikivoyage/en/thumb/e/e9/GoTBanner1.jpg/2550px-GoTBanner1.jpg 1.5x, //upload.wikimedia.org/wikivoyage/en/thumb/e/e9/GoTBanner1.jpg/3400px-GoTBanner1.jpg 2x\" data-file-width=\"3600\" data-file-height=\"1200\" width=\"1700\" height=\"567\">\n</p>\n\t<a href=\"/wiki/Game_of_Thrones_tourism\" title=\"Game of Thrones tourism\"><img alt=\"Game of Thrones tourism\" src=\"//upload.wikimedia.org/wikivoyage/en/thumb/e/e9/GoTBanner1.jpg/1700px-GoTBanner1.jpg\" decoding=\"async\" srcset=\"//upload.wikimedia.org/wikivoyage/en/thumb/e/e9/GoTBanner1.jpg/2550px-GoTBanner1.jpg 1.5x, //upload.wikimedia.org/wikivoyage/en/thumb/e/e9/GoTBanner1.jpg/3400px-GoTBanner1.jpg 2x\" data-file-width=\"3600\" data-file-height=\"1200\" width=\"1700\" height=\"567\"></a></div>","link":"https://en.wikivoyage.org/wiki/Game_of_Thrones_tourism","retrieved":1632202827901}]}