{"title":"Combined feed","url":"https://Vinnl.github.io/feeds/all.xml","elements":[{"title":"Thomas Resetarits (Wikipedia — did you know?)","contents":"... that <a href=\"/wiki/Burgenland_Croats\" title=\"Burgenland Croats\">Burgenland Croat</a> sculptor <b><a href=\"/wiki/Thomas_Resetarits\" title=\"Thomas Resetarits\">Thomas Resetarits</a></b> created <a href=\"/wiki/Stations_of_the_Cross\" title=\"Stations of the Cross\">Stations of the Cross</a> <i>(example sculpture pictured)</i>?","link":"https://en.wikipedia.org/wiki/Thomas_Resetarits","retrieved":1655876524116},{"title":"Canyon Kid's Corner (Wikipedia — did you know?)","contents":"... that the host of <i><b><a href=\"/wiki/Canyon_Kid%27s_Corner\" title=\"Canyon Kid's Corner\">Canyon Kid's Corner</a></b></i> said that his <a href=\"/wiki/New_York_accent\" title=\"New York accent\">Brooklyn accent</a> as a cowboy came from \"the canyons created by the tall buildings\"?","link":"https://en.wikipedia.org/wiki/Canyon_Kid%27s_Corner","retrieved":1655876524119},{"title":"Let's Go Karaoke! (Wikipedia — did you know?)","contents":"... that after a publisher declined the manga series <i><b><a href=\"/wiki/Let%27s_Go_Karaoke!\" title=\"Let's Go Karaoke!\">Let's Go Karaoke!</a></b></i>, it sold out multiple times after <a href=\"/wiki/Doujinshi\" title=\"Doujinshi\">being self-published</a>?","link":"https://en.wikipedia.org/wiki/Let%27s_Go_Karaoke!","retrieved":1655876524120},{"title":"Vito Trause (Wikipedia — did you know?)","contents":"... that <b><a href=\"/wiki/Vito_Trause\" title=\"Vito Trause\">Vito Trause</a></b>, who dropped out of high school during his junior year to join the <a href=\"/wiki/United_States_Army\" title=\"United States Army\">United States Army</a> in 1943, received his <a href=\"/wiki/High_school_diploma\" title=\"High school diploma\">high school diploma</a> at the age of 92?","link":"https://en.wikipedia.org/wiki/Vito_Trause","retrieved":1655876524121},{"title":"Mujh Se Pehli Si Mohabbat Mere Mehboob Na Maang (Wikipedia — did you know?)","contents":"... that <a href=\"/wiki/Faiz_Ahmad_Faiz\" title=\"Faiz Ahmad Faiz\">Faiz Ahmad Faiz</a> reportedly remarked that <b><a href=\"/wiki/Mujh_Se_Pehli_Si_Mohabbat_Mere_Mehboob_Na_Maang\" title=\"Mujh Se Pehli Si Mohabbat Mere Mehboob Na Maang\">Mujh Se Pehli Si Mohabbat Mere Mehboob Na Maang</a></b> no longer belonged to him but to <a href=\"/wiki/Noor_Jehan\" title=\"Noor Jehan\">Noor Jehan</a>?","link":"https://en.wikipedia.org/wiki/Mujh_Se_Pehli_Si_Mohabbat_Mere_Mehboob_Na_Maang","retrieved":1655876524122},{"title":"song in The Last of Us Part II (Wikipedia — did you know?)","contents":"... that <a href=\"/wiki/Pearl_Jam\" title=\"Pearl Jam\">Pearl Jam</a>'s manager agreed to include a <b><a href=\"/wiki/Music_of_The_Last_of_Us_Part_II\" title=\"Music of The Last of Us Part II\">song in <i>The Last of Us Part&nbsp;II</i></a></b> after hearing the story pitch, watching the trailer, and receiving a <a href=\"/wiki/PlayStation_4\" title=\"PlayStation 4\">PlayStation 4</a> and a copy of <a href=\"/wiki/The_Last_of_Us\" title=\"The Last of Us\">the first game</a>?","link":"https://en.wikipedia.org/wiki/Music_of_The_Last_of_Us_Part_II","retrieved":1655876524122},{"title":"Anna October (Wikipedia — did you know?)","contents":"... that Ukrainian designer <b><a href=\"/wiki/Anna_October\" title=\"Anna October\">Anna October</a></b> showed her collection during Paris Fashion Week after escaping the <a href=\"/wiki/2022_Russian_invasion_of_Ukraine\" title=\"2022 Russian invasion of Ukraine\">2022 Russian invasion of Ukraine</a>?","link":"https://en.wikipedia.org/wiki/Anna_October","retrieved":1655876524124},{"title":"it was KOOL in Phoenix (Wikipedia — did you know?)","contents":"... that 75 years ago today, <b><a href=\"/wiki/KKNT\" title=\"KKNT\">it was KOOL in Phoenix</a></b>?","link":"https://en.wikipedia.org/wiki/KKNT","retrieved":1655876524124},{"title":"Dublin (Wikivoyage recommendations)","contents":"<style data-mw-deduplicate=\"TemplateStyles:r3732050\">.mw-parser-output .mainpage-shadowbox{color:white;background:rgb(16,16,16);background:rgba(0,0,0,0.3);border-radius:4px}.mw-parser-output .mainpage-shadowbox h2,.mw-parser-output .mainpage-shadowbox h3{color:white;border:none;font-family:sans-serif;line-height:1.2em;margin:0;padding:0}.mw-parser-output .mainpage-shadowbox a{color:white;font-weight:bold}.mw-parser-output .banner-image{position:relative;max-width:1125px;height:auto;margin-bottom:.6em}.mw-parser-output .banner-image img{max-width:100%;height:auto}.mw-parser-output .banner-box-wide{width:80%}.mw-parser-output .banner-box-left,.mw-parser-output .banner-box-right{padding:8px 7px;background:rgb(16,16,16);background:rgba(0,0,0,0.3);border-radius:4px;width:40%}.mw-parser-output .banner-box-left{text-align:left}.mw-parser-output .banner-box-right{text-align:right}.mw-parser-output .banner-box-2{position:absolute;z-index:2;min-width:20em}@media screen and (min-width:720px){.mw-parser-output .banner-image img.nolink{display:none}.mw-parser-output .mainpage-shadowbox h2{font-size:190%}.mw-parser-output .mainpage-shadowbox h3{font-size:150%}.mw-parser-output .banner-image{overflow:hidden}.mw-parser-output .banner-box-left{left:3%}.mw-parser-output .banner-box-right{right:3%}.mw-parser-output .banner-box-2{margin-top:2em}.mw-parser-output .banner-box-2 .quote{font-size:80%;line-height:1.2em}}@media screen and (max-width:720px){.mw-parser-output .banner-image img:not(.nolink){display:none}.mw-parser-output .banner-image>.mainpage-shadowbox{width:inherit!important;min-height:100%;margin-left:-150%;margin-right:150%;opacity:0;background:black}.mw-parser-output .mainpage-shadowbox .quote>a:after{content:\"\\a Tap to learn more.\";white-space:pre}.mw-parser-output .jcarousel-item:hover .mainpage-shadowbox{margin:unset;opacity:1;transition:margin 0.5s;bottom:50%}.mw-parser-output .jcarousel-control-prev,.mw-parser-output .jcarousel-control-next{display:none}.mw-parser-output .interactiveIcon{position:absolute;opacity:0.4;height:75%!important;width:auto;bottom:0;right:0}}</style>\n<div class=\"banner-image js-proportonal-resize\" style=\"font-size: 117.222%;\">\n<p>\t<img alt=\"Interactive icon.svg\" src=\"//upload.wikimedia.org/wikipedia/commons/thumb/e/e6/Interactive_icon.svg/220px-Interactive_icon.svg.png\" decoding=\"async\" class=\"nolink interactiveIcon\" srcset=\"//upload.wikimedia.org/wikipedia/commons/thumb/e/e6/Interactive_icon.svg/330px-Interactive_icon.svg.png 1.5x, //upload.wikimedia.org/wikipedia/commons/thumb/e/e6/Interactive_icon.svg/440px-Interactive_icon.svg.png 2x\" data-file-width=\"133\" data-file-height=\"200\" width=\"220\" height=\"331\">\n</p>\n\t<div class=\"mainpage-shadowbox banner-box-2 banner-box-right\">\n\t\t<h2><span class=\"mw-headline\" id=\"Dublin\"><a href=\"/wiki/Dublin\" title=\"Dublin\">Dublin</a></span></h2>\n\t\t<h3><span class=\"mw-headline\" id=\"Destination_of_the_month\"><a href=\"/wiki/Previous_Destinations_of_the_month\" title=\"Previous Destinations of the month\">Destination of the month</a></span></h3>\n\t\t<div class=\"quote\"><a href=\"/wiki/Dublin\" title=\"Dublin\">Ireland's capital is a friendly, cosmopolitan city with the best of the country's music and nightlife, with Bloomsday celebrated on 16 June.</a></div>\n\t</div>\n<p>\t<img alt=\"Dublin\" src=\"//upload.wikimedia.org/wikipedia/commons/thumb/6/65/Dublin_Wikivoyage_DOTM_banner_002.jpg/1700px-Dublin_Wikivoyage_DOTM_banner_002.jpg\" decoding=\"async\" title=\"Dublin\" class=\"nolink\" srcset=\"//upload.wikimedia.org/wikipedia/commons/6/65/Dublin_Wikivoyage_DOTM_banner_002.jpg 1.5x\" data-file-width=\"2048\" data-file-height=\"683\" width=\"1700\" height=\"567\">\n</p>\n\t<a href=\"/wiki/Dublin\" title=\"Dublin\"><img alt=\"Dublin\" src=\"//upload.wikimedia.org/wikipedia/commons/thumb/6/65/Dublin_Wikivoyage_DOTM_banner_002.jpg/1700px-Dublin_Wikivoyage_DOTM_banner_002.jpg\" decoding=\"async\" srcset=\"//upload.wikimedia.org/wikipedia/commons/6/65/Dublin_Wikivoyage_DOTM_banner_002.jpg 1.5x\" data-file-width=\"2048\" data-file-height=\"683\" width=\"1700\" height=\"567\"></a></div>","link":"https://en.wikivoyage.org/wiki/Dublin","retrieved":1654063318361},{"title":"Homer (Wikivoyage recommendations)","contents":"<link rel=\"mw-deduplicated-inline-style\" href=\"mw-data:TemplateStyles:r3732050\">\n<div class=\"banner-image js-proportonal-resize\" style=\"font-size: 117.222%;\">\n<p>\t<img alt=\"Interactive icon.svg\" src=\"//upload.wikimedia.org/wikipedia/commons/thumb/e/e6/Interactive_icon.svg/220px-Interactive_icon.svg.png\" decoding=\"async\" class=\"nolink interactiveIcon\" srcset=\"//upload.wikimedia.org/wikipedia/commons/thumb/e/e6/Interactive_icon.svg/330px-Interactive_icon.svg.png 1.5x, //upload.wikimedia.org/wikipedia/commons/thumb/e/e6/Interactive_icon.svg/440px-Interactive_icon.svg.png 2x\" data-file-width=\"133\" data-file-height=\"200\" width=\"220\" height=\"331\">\n</p>\n\t<div class=\"mainpage-shadowbox banner-box-2 banner-box-right\" style=\"width:30%\">\n\t\t<h2><span class=\"mw-headline\" id=\"Homer\"><a href=\"/wiki/Homer\" title=\"Homer\">Homer</a></span></h2>\n\t\t<h3><span class=\"mw-headline\" id=\"Off_the_Beaten_Path\"><a href=\"/wiki/Previously_Off_the_beaten_path\" title=\"Previously Off the beaten path\">Off the Beaten Path</a></span></h3>\n\t\t<div class=\"quote\"><a href=\"/wiki/Homer\" title=\"Homer\">The Halibut Fishing Capital of the World is the western end of the American highway system, and has an astounding view of Alaska's southern coast.</a></div>\n\t</div>\n<p>\t<img alt=\"Homer\" src=\"//upload.wikimedia.org/wikipedia/commons/thumb/9/99/Homer_otbp_banner_1.jpg/1700px-Homer_otbp_banner_1.jpg\" decoding=\"async\" title=\"Homer\" class=\"nolink\" srcset=\"//upload.wikimedia.org/wikipedia/commons/thumb/9/99/Homer_otbp_banner_1.jpg/2550px-Homer_otbp_banner_1.jpg 1.5x, //upload.wikimedia.org/wikipedia/commons/thumb/9/99/Homer_otbp_banner_1.jpg/3400px-Homer_otbp_banner_1.jpg 2x\" data-file-width=\"5181\" data-file-height=\"1728\" width=\"1700\" height=\"567\">\n</p>\n\t<a href=\"/wiki/Homer\" title=\"Homer\"><img alt=\"Homer\" src=\"//upload.wikimedia.org/wikipedia/commons/thumb/9/99/Homer_otbp_banner_1.jpg/1700px-Homer_otbp_banner_1.jpg\" decoding=\"async\" srcset=\"//upload.wikimedia.org/wikipedia/commons/thumb/9/99/Homer_otbp_banner_1.jpg/2550px-Homer_otbp_banner_1.jpg 1.5x, //upload.wikimedia.org/wikipedia/commons/thumb/9/99/Homer_otbp_banner_1.jpg/3400px-Homer_otbp_banner_1.jpg 2x\" data-file-width=\"5181\" data-file-height=\"1728\" width=\"1700\" height=\"567\"></a></div>","link":"https://en.wikivoyage.org/wiki/Homer","retrieved":1654925875970},{"title":"Wine regions of Ontario (Wikivoyage recommendations)","contents":"<link rel=\"mw-deduplicated-inline-style\" href=\"mw-data:TemplateStyles:r3732050\">\n<div class=\"banner-image js-proportonal-resize\" style=\"font-size: 117.222%;\">\n<p>\t<img alt=\"Interactive icon.svg\" src=\"//upload.wikimedia.org/wikipedia/commons/thumb/e/e6/Interactive_icon.svg/220px-Interactive_icon.svg.png\" decoding=\"async\" class=\"nolink interactiveIcon\" srcset=\"//upload.wikimedia.org/wikipedia/commons/thumb/e/e6/Interactive_icon.svg/330px-Interactive_icon.svg.png 1.5x, //upload.wikimedia.org/wikipedia/commons/thumb/e/e6/Interactive_icon.svg/440px-Interactive_icon.svg.png 2x\" data-file-width=\"133\" data-file-height=\"200\" width=\"220\" height=\"331\">\n</p>\n\t<div class=\"mainpage-shadowbox banner-box-2 banner-box-right\" style=\"width:30%\">\n\t\t<h2><span class=\"mw-headline\" id=\"Wine_regions_of_Ontario\"><a href=\"/wiki/Wine_regions_of_Ontario\" title=\"Wine regions of Ontario\">Wine regions of Ontario</a></span></h2>\n\t\t<h3><span class=\"mw-headline\" id=\"Featured_Travel_Topic\"><a href=\"/wiki/Previous_Featured_travel_topics\" title=\"Previous Featured travel topics\">Featured Travel Topic</a></span></h3>\n\t\t<div class=\"quote\"><a href=\"/wiki/Wine_regions_of_Ontario\" title=\"Wine regions of Ontario\">Discover Canada's largest wine region, and its wide variety of cool climate wines.</a></div>\n\t</div>\n<p>\t<img alt=\"Wine regions of Ontario\" src=\"//upload.wikimedia.org/wikipedia/commons/1/1e/Wikivoyage_banner_wines_of_ontario_2.jpg\" decoding=\"async\" title=\"Wine regions of Ontario\" class=\"nolink\" data-file-width=\"1280\" data-file-height=\"426\" width=\"1280\" height=\"426\">\n</p>\n\t<a href=\"/wiki/Wine_regions_of_Ontario\" title=\"Wine regions of Ontario\"><img alt=\"Wine regions of Ontario\" src=\"//upload.wikimedia.org/wikipedia/commons/1/1e/Wikivoyage_banner_wines_of_ontario_2.jpg\" decoding=\"async\" data-file-width=\"1280\" data-file-height=\"426\" width=\"1280\" height=\"426\"></a></div>","link":"https://en.wikivoyage.org/wiki/Wine_regions_of_Ontario","retrieved":1655833901932}]}