{"title":"Combined feed","url":"https://Vinnl.github.io/feeds/all.xml","elements":[{"title":"Allegory of Patience (Wikipedia — did you know?)","contents":"... that contemporary correspondence contributed to the identification of <a href=\"/wiki/Giorgio_Vasari\" title=\"Giorgio Vasari\">Vasari</a>'s <i><b><a href=\"/wiki/Allegory_of_Patience_(Vasari)\" title=\"Allegory of Patience (Vasari)\">Allegory of Patience</a></b></i> <i>(pictured)</i>?","link":"https://en.wikipedia.org/wiki/Allegory_of_Patience_(Vasari)","retrieved":1637991549766},{"title":"Malang city council (Wikipedia — did you know?)","contents":"... that in 2018, 41 out of 45 members of the <b><a href=\"/wiki/Malang_City_Regional_People%27s_Representative_Council\" title=\"Malang City Regional People's Representative Council\">Malang city council</a></b> were arrested for corruption?","link":"https://en.wikipedia.org/wiki/Malang_City_Regional_People%27s_Representative_Council","retrieved":1637991549768},{"title":"Rhapsody (Wikipedia — did you know?)","contents":"... that <a href=\"/wiki/Frederick_Ashton\" title=\"Frederick Ashton\">Frederick Ashton</a> choreographed the ballet <i><b><a href=\"/wiki/Rhapsody_(Ashton)\" title=\"Rhapsody (Ashton)\">Rhapsody</a></b></i> for both <a href=\"/wiki/Queen_Elizabeth_The_Queen_Mother\" title=\"Queen Elizabeth The Queen Mother\">Queen Elizabeth The Queen Mother</a>'s 80th birthday, and <a href=\"/wiki/Mikhail_Baryshnikov\" title=\"Mikhail Baryshnikov\">Mikhail Baryshnikov</a>'s guest appearance with <a href=\"/wiki/The_Royal_Ballet\" title=\"The Royal Ballet\">the Royal Ballet</a>?","link":"https://en.wikipedia.org/wiki/Rhapsody_(Ashton)","retrieved":1637991549770},{"title":"KNCR (Wikipedia — did you know?)","contents":"... that California radio station <b><a href=\"/wiki/KNCR\" title=\"KNCR\">KNCR</a></b> was fined by the <a href=\"/wiki/Federal_Communications_Commission\" title=\"Federal Communications Commission\">Federal Communications Commission</a> for moving its transmitter site without permission after being evicted?","link":"https://en.wikipedia.org/wiki/KNCR","retrieved":1637991549771},{"title":"rock from New Caledonia (Wikipedia — did you know?)","contents":"... that the most significant <b><a href=\"/wiki/Geology_of_New_Caledonia\" title=\"Geology of New Caledonia\">rock from New Caledonia</a></b> is <a href=\"/wiki/Peridotite\" title=\"Peridotite\">peridotite</a>, which comes from the <a href=\"/wiki/Earth%27s_mantle\" title=\"Earth's mantle\">Earth's mantle</a>?","link":"https://en.wikipedia.org/wiki/Geology_of_New_Caledonia","retrieved":1637991549775},{"title":"Alex Miller (Wikipedia — did you know?)","contents":"... that <a href=\"/wiki/UMass_Minutemen_football\" title=\"UMass Minutemen football\">UMass</a> interim football coach <b><a href=\"/wiki/Alex_Miller_(American_football_coach)\" title=\"Alex Miller (American football coach)\">Alex Miller</a></b> started in all fifty games of his playing career at UMass?","link":"https://en.wikipedia.org/wiki/Alex_Miller_(American_football_coach)","retrieved":1637991549777},{"title":"Speak Now (Wikipedia — did you know?)","contents":"... that with the album <i><b><a href=\"/wiki/Speak_Now\" title=\"Speak Now\">Speak Now</a></b></i>, <a href=\"/wiki/Taylor_Swift\" title=\"Taylor Swift\">Taylor Swift</a> became the first female musician to have 11 songs on the <a href=\"/wiki/Billboard_Hot_100\" title=\"Billboard Hot 100\"><i>Billboard</i> Hot&nbsp;100</a> in the same week?","link":"https://en.wikipedia.org/wiki/Speak_Now","retrieved":1637991549778},{"title":"Fish-MIP (Wikipedia — did you know?)","contents":"... that <a href=\"/wiki/Ecosystem_model\" title=\"Ecosystem model\">models</a> couple up at <b><a href=\"/wiki/Fisheries_and_Marine_Ecosystem_Model_Intercomparison_Project\" title=\"Fisheries and Marine Ecosystem Model Intercomparison Project\">Fish-MIP</a></b>?","link":"https://en.wikipedia.org/wiki/Fisheries_and_Marine_Ecosystem_Model_Intercomparison_Project","retrieved":1637991549780},{"title":"Alexandria (Wikivoyage recommendations)","contents":"<style data-mw-deduplicate=\"TemplateStyles:r3732050\">.mw-parser-output .mainpage-shadowbox{color:white;background:rgb(16,16,16);background:rgba(0,0,0,0.3);border-radius:4px}.mw-parser-output .mainpage-shadowbox h2,.mw-parser-output .mainpage-shadowbox h3{color:white;border:none;font-family:sans-serif;line-height:1.2em;margin:0;padding:0}.mw-parser-output .mainpage-shadowbox a{color:white;font-weight:bold}.mw-parser-output .banner-image{position:relative;max-width:1125px;height:auto;margin-bottom:.6em}.mw-parser-output .banner-image img{max-width:100%;height:auto}.mw-parser-output .banner-box-wide{width:80%}.mw-parser-output .banner-box-left,.mw-parser-output .banner-box-right{padding:8px 7px;background:rgb(16,16,16);background:rgba(0,0,0,0.3);border-radius:4px;width:40%}.mw-parser-output .banner-box-left{text-align:left}.mw-parser-output .banner-box-right{text-align:right}.mw-parser-output .banner-box-2{position:absolute;z-index:2;min-width:20em}@media screen and (min-width:720px){.mw-parser-output .banner-image img.nolink{display:none}.mw-parser-output .mainpage-shadowbox h2{font-size:190%}.mw-parser-output .mainpage-shadowbox h3{font-size:150%}.mw-parser-output .banner-image{overflow:hidden}.mw-parser-output .banner-box-left{left:3%}.mw-parser-output .banner-box-right{right:3%}.mw-parser-output .banner-box-2{margin-top:2em}.mw-parser-output .banner-box-2 .quote{font-size:80%;line-height:1.2em}}@media screen and (max-width:720px){.mw-parser-output .banner-image img:not(.nolink){display:none}.mw-parser-output .banner-image>.mainpage-shadowbox{width:inherit!important;min-height:100%;margin-left:-150%;margin-right:150%;opacity:0;background:black}.mw-parser-output .mainpage-shadowbox .quote>a:after{content:\"\\a Tap to learn more.\";white-space:pre}.mw-parser-output .jcarousel-item:hover .mainpage-shadowbox{margin:unset;opacity:1;transition:margin 0.5s;bottom:50%}.mw-parser-output .jcarousel-control-prev,.mw-parser-output .jcarousel-control-next{display:none}.mw-parser-output .interactiveIcon{position:absolute;opacity:0.4;height:75%!important;width:auto;bottom:0;right:0}}</style>\n<div class=\"banner-image js-proportonal-resize\" style=\"font-size: 117.222%;\">\n<p>\t<img alt=\"Interactive icon.svg\" src=\"//upload.wikimedia.org/wikipedia/commons/thumb/e/e6/Interactive_icon.svg/220px-Interactive_icon.svg.png\" decoding=\"async\" class=\"nolink interactiveIcon\" srcset=\"//upload.wikimedia.org/wikipedia/commons/thumb/e/e6/Interactive_icon.svg/330px-Interactive_icon.svg.png 1.5x, //upload.wikimedia.org/wikipedia/commons/thumb/e/e6/Interactive_icon.svg/440px-Interactive_icon.svg.png 2x\" data-file-width=\"133\" data-file-height=\"200\" width=\"220\" height=\"331\">\n</p>\n\t<div class=\"mainpage-shadowbox banner-box-2 banner-box-right\" style=\"width:40%\">\n\t\t<h2><span class=\"mw-headline\" id=\"Alexandria\"><a href=\"/wiki/Alexandria\" title=\"Alexandria\">Alexandria</a></span></h2>\n\t\t<h3><span class=\"mw-headline\" id=\"Destination_of_the_Month\"><a href=\"/wiki/Previous_Destinations_of_the_Month\" class=\"mw-redirect\" title=\"Previous Destinations of the Month\">Destination of the Month</a></span></h3>\n\t\t<div class=\"quote\"><a href=\"/wiki/Alexandria\" title=\"Alexandria\">Egypt's window to the Mediterranean is truly a city with a history, and also famous for its seafood and long beach promenade - the Corniche.</a></div>\n\t</div>\n<p>\t<img alt=\"Alexandria\" src=\"//upload.wikimedia.org/wikivoyage/en/b/be/Alexandria_DOTM_Banner_4.jpg\" decoding=\"async\" title=\"Alexandria\" class=\"nolink\" data-file-width=\"1700\" data-file-height=\"567\" width=\"1700\" height=\"567\">\n</p>\n\t<a href=\"/wiki/Alexandria\" title=\"Alexandria\"><img alt=\"Alexandria\" src=\"//upload.wikimedia.org/wikivoyage/en/b/be/Alexandria_DOTM_Banner_4.jpg\" decoding=\"async\" data-file-width=\"1700\" data-file-height=\"567\" width=\"1700\" height=\"567\"></a></div>","link":"https://en.wikivoyage.org/wiki/Alexandria","retrieved":1635745124694},{"title":"Plymouth (Massachusetts) (Wikivoyage recommendations)","contents":"<link rel=\"mw-deduplicated-inline-style\" href=\"mw-data:TemplateStyles:r3732050\">\n<div class=\"banner-image js-proportonal-resize\" style=\"font-size: 117.222%;\">\n<p>\t<img alt=\"Interactive icon.svg\" src=\"//upload.wikimedia.org/wikipedia/commons/thumb/e/e6/Interactive_icon.svg/220px-Interactive_icon.svg.png\" decoding=\"async\" class=\"nolink interactiveIcon\" srcset=\"//upload.wikimedia.org/wikipedia/commons/thumb/e/e6/Interactive_icon.svg/330px-Interactive_icon.svg.png 1.5x, //upload.wikimedia.org/wikipedia/commons/thumb/e/e6/Interactive_icon.svg/440px-Interactive_icon.svg.png 2x\" data-file-width=\"133\" data-file-height=\"200\" width=\"220\" height=\"331\">\n</p>\n\t<div class=\"mainpage-shadowbox banner-box-2 banner-box-right\" style=\"width:40%\">\n\t\t<h2><span id=\"Plymouth_.28Massachusetts.29\"></span><span class=\"mw-headline\" id=\"Plymouth_(Massachusetts)\"><a href=\"/wiki/Plymouth_(Massachusetts)\" title=\"Plymouth (Massachusetts)\">Plymouth (Massachusetts)</a></span></h2>\n\t\t<h3><span class=\"mw-headline\" id=\"Off_the_beaten_path\"><a href=\"/wiki/Previously_Off_the_beaten_path\" title=\"Previously Off the beaten path\">Off the beaten path</a></span></h3>\n\t\t<div class=\"quote\"><a href=\"/wiki/Plymouth_(Massachusetts)\" title=\"Plymouth (Massachusetts)\">New England's first colony saw the foundation of the Thanksgiving holiday in 1621, and keeps four centuries of heritage alive.</a></div>\n\t</div>\n<p>\t<img alt=\"Plymouth (Massachusetts)\" src=\"//upload.wikimedia.org/wikipedia/commons/thumb/4/4c/Twilight_Plymouth_MA_Wikivoyage_DOTM_banner.jpg/1700px-Twilight_Plymouth_MA_Wikivoyage_DOTM_banner.jpg\" decoding=\"async\" title=\"Plymouth (Massachusetts)\" class=\"nolink\" srcset=\"//upload.wikimedia.org/wikipedia/commons/thumb/4/4c/Twilight_Plymouth_MA_Wikivoyage_DOTM_banner.jpg/2550px-Twilight_Plymouth_MA_Wikivoyage_DOTM_banner.jpg 1.5x, //upload.wikimedia.org/wikipedia/commons/thumb/4/4c/Twilight_Plymouth_MA_Wikivoyage_DOTM_banner.jpg/3400px-Twilight_Plymouth_MA_Wikivoyage_DOTM_banner.jpg 2x\" data-file-width=\"7000\" data-file-height=\"2334\" width=\"1700\" height=\"567\">\n</p>\n\t<a href=\"/wiki/Plymouth_(Massachusetts)\" title=\"Plymouth (Massachusetts)\"><img alt=\"Plymouth (Massachusetts)\" src=\"//upload.wikimedia.org/wikipedia/commons/thumb/4/4c/Twilight_Plymouth_MA_Wikivoyage_DOTM_banner.jpg/1700px-Twilight_Plymouth_MA_Wikivoyage_DOTM_banner.jpg\" decoding=\"async\" srcset=\"//upload.wikimedia.org/wikipedia/commons/thumb/4/4c/Twilight_Plymouth_MA_Wikivoyage_DOTM_banner.jpg/2550px-Twilight_Plymouth_MA_Wikivoyage_DOTM_banner.jpg 1.5x, //upload.wikimedia.org/wikipedia/commons/thumb/4/4c/Twilight_Plymouth_MA_Wikivoyage_DOTM_banner.jpg/3400px-Twilight_Plymouth_MA_Wikivoyage_DOTM_banner.jpg 2x\" data-file-width=\"7000\" data-file-height=\"2334\" width=\"1700\" height=\"567\"></a></div>","link":"https://en.wikivoyage.org/wiki/Plymouth_(Massachusetts)","retrieved":1636695610592},{"title":"Pacific War (Wikivoyage recommendations)","contents":"<link rel=\"mw-deduplicated-inline-style\" href=\"mw-data:TemplateStyles:r3732050\">\n<div class=\"banner-image js-proportonal-resize\" style=\"font-size: 117.222%;\">\n<p>\t<img alt=\"Interactive icon.svg\" src=\"//upload.wikimedia.org/wikipedia/commons/thumb/e/e6/Interactive_icon.svg/220px-Interactive_icon.svg.png\" decoding=\"async\" class=\"nolink interactiveIcon\" srcset=\"//upload.wikimedia.org/wikipedia/commons/thumb/e/e6/Interactive_icon.svg/330px-Interactive_icon.svg.png 1.5x, //upload.wikimedia.org/wikipedia/commons/thumb/e/e6/Interactive_icon.svg/440px-Interactive_icon.svg.png 2x\" data-file-width=\"133\" data-file-height=\"200\" width=\"220\" height=\"331\">\n</p>\n\t<div class=\"mainpage-shadowbox banner-box-2 banner-box-left\">\n\t\t<h2><span class=\"mw-headline\" id=\"Pacific_War\"><a href=\"/wiki/Pacific_War\" title=\"Pacific War\">Pacific War</a></span></h2>\n\t\t<h3><span class=\"mw-headline\" id=\"Featured_Travel_Topic\"><a href=\"/wiki/Previous_Featured_travel_topics\" title=\"Previous Featured travel topics\">Featured Travel Topic</a></span></h3>\n\t\t<div class=\"quote\"><a href=\"/wiki/Pacific_War\" title=\"Pacific War\">World War II came to the Pacific Ocean on 7 December 1941, and was fought across seas and jungles with devastating weapons.</a></div>\n\t</div>\n<p>\t<img alt=\"Pacific War\" src=\"//upload.wikimedia.org/wikivoyage/en/thumb/2/25/Nuclear_tourism_banner_1.jpg/1700px-Nuclear_tourism_banner_1.jpg\" decoding=\"async\" title=\"Pacific War\" class=\"nolink\" srcset=\"//upload.wikimedia.org/wikivoyage/en/thumb/2/25/Nuclear_tourism_banner_1.jpg/2550px-Nuclear_tourism_banner_1.jpg 1.5x, //upload.wikimedia.org/wikivoyage/en/thumb/2/25/Nuclear_tourism_banner_1.jpg/3400px-Nuclear_tourism_banner_1.jpg 2x\" data-file-width=\"3456\" data-file-height=\"1152\" width=\"1700\" height=\"567\">\n</p>\n\t<a href=\"/wiki/Pacific_War\" title=\"Pacific War\"><img alt=\"Pacific War\" src=\"//upload.wikimedia.org/wikivoyage/en/thumb/2/25/Nuclear_tourism_banner_1.jpg/1700px-Nuclear_tourism_banner_1.jpg\" decoding=\"async\" srcset=\"//upload.wikimedia.org/wikivoyage/en/thumb/2/25/Nuclear_tourism_banner_1.jpg/2550px-Nuclear_tourism_banner_1.jpg 1.5x, //upload.wikimedia.org/wikivoyage/en/thumb/2/25/Nuclear_tourism_banner_1.jpg/3400px-Nuclear_tourism_banner_1.jpg 2x\" data-file-width=\"3456\" data-file-height=\"1152\" width=\"1700\" height=\"567\"></a></div>","link":"https://en.wikivoyage.org/wiki/Pacific_War","retrieved":1637516603735}]}