{"title":"Wikipedia — did you know?","url":"https://en.wikipedia.org/wiki/Main_Page","favicon":"https://en.wikipedia.org/static/favicon/wikipedia.ico","elements":[{"title":"Palae­orehniidae","contents":"... that with all known <b><a href=\"/wiki/Palaeorehniidae\" title=\"Palaeorehniidae\">Palae­orehniidae</a></b> fossils <i>(example pictured)</i> being incomplete, the relationships of the family are uncertain?","link":"https://en.wikipedia.org/wiki/Palaeorehniidae","retrieved":1693546654156},{"title":"something they can do with it","contents":"... that when Kentuckians discover unwanted bourbon, there is <b><a href=\"/wiki/Revival_Vintage_Bottle_Shop\" title=\"Revival Vintage Bottle Shop\">something they can do with it</a></b>?","link":"https://en.wikipedia.org/wiki/Revival_Vintage_Bottle_Shop","retrieved":1693546654157},{"title":"William J. Murphy","contents":"... that <b><a href=\"/wiki/William_J._Murphy_(Jesuit)\" title=\"William J. Murphy (Jesuit)\">William J. Murphy</a></b><span class=\"nowrap\">'s</span> presidency of <a href=\"/wiki/Boston_College\" title=\"Boston College\">Boston College</a> began 16 days before the start of <a href=\"/wiki/World_War_II\" title=\"World War II\">World War&nbsp;II</a> and concluded five days after hostilities ended?","link":"https://en.wikipedia.org/wiki/William_J._Murphy_(Jesuit)","retrieved":1693546654163},{"title":"their controversial purchase of condominium units","contents":"... that Singapore's founding prime minister <a href=\"/wiki/Lee_Kuan_Yew\" title=\"Lee Kuan Yew\">Lee Kuan Yew</a> and his son <a href=\"/wiki/Lee_Hsien_Loong\" title=\"Lee Hsien Loong\">Lee Hsien Loong</a> donated the \"unsolicited discounts\" from <b><a href=\"/wiki/1995_Hotel_Properties_Limited_apartment_sales\" title=\"1995 Hotel Properties Limited apartment sales\">their controversial purchase of condominium units</a></b> to charity?","link":"https://en.wikipedia.org/wiki/1995_Hotel_Properties_Limited_apartment_sales","retrieved":1693546654164},{"title":"Sienna Shaw","contents":"... that <b><a href=\"/wiki/Sienna_Shaw\" title=\"Sienna Shaw\">Sienna Shaw</a></b> of the slasher film <i><a href=\"/wiki/Terrifier_2\" title=\"Terrifier 2\">Terrifier&nbsp;2</a></i> was envisioned by <a href=\"/wiki/Damien_Leone\" title=\"Damien Leone\">Damien Leone</a> as symbolizing an <a href=\"/wiki/Old_Testament\" title=\"Old Testament\">Old Testament</a> angel?","link":"https://en.wikipedia.org/wiki/Sienna_Shaw","retrieved":1693546654166},{"title":"Le Vin herbé","contents":"... that <i><b><a href=\"/wiki/Le_Vin_herb%C3%A9\" title=\"Le Vin herbé\">Le Vin herbé</a></b></i> is a 1942 musical setting of the story of <a href=\"/wiki/Tristan_and_Iseult\" title=\"Tristan and Iseult\">Tristan and Iseult</a> by <a href=\"/wiki/Frank_Martin_(composer)\" title=\"Frank Martin (composer)\">Frank Martin</a> for twelve vocalists, seven <a href=\"/wiki/String_instrument\" title=\"String instrument\">strings</a> and <a href=\"/wiki/Piano\" title=\"Piano\">piano</a>?","link":"https://en.wikipedia.org/wiki/Le_Vin_herb%C3%A9","retrieved":1693546654169},{"title":"Casey Johnston","contents":"... that <b><a href=\"/wiki/Casey_Johnston\" title=\"Casey Johnston\">Casey Johnston</a></b><span class=\"nowrap\">'s</span> writing about weightlifting is intended for people who feel their bodies are \"never hot enough\"?","link":"https://en.wikipedia.org/wiki/Casey_Johnston","retrieved":1693546654172},{"title":"Philly 57","contents":"... that today is independence day for <b><a href=\"/wiki/WPSG\" title=\"WPSG\">Philly&nbsp;57</a></b>?","link":"https://en.wikipedia.org/wiki/WPSG","retrieved":1693546654175}]}