{"title":"Wikipedia — did you know?","url":"https://en.wikipedia.org/wiki/Main_Page","favicon":"https://en.wikipedia.org/static/favicon/wikipedia.ico","elements":[{"title":"Al-Asma'i","contents":"... that the magazine <i><b><a href=\"/wiki/Al-Asma%27i_(magazine)\" title=\"Al-Asma'i (magazine)\">Al-Asma'i</a></b></i> <i>(pictured)</i>, one of the first <a href=\"/wiki/History_of_Palestinian_journalism\" title=\"History of Palestinian journalism\">publications to emerge in Ottoman Palestine</a> in 1908, was <a href=\"/wiki/Anti-Zionism\" title=\"Anti-Zionism\">opposed to Zionism</a> and frequently criticized <a href=\"/wiki/Aliyah\" title=\"Aliyah\">Jewish immigration</a>?","link":"https://en.wikipedia.org/wiki/Al-Asma%27i_(magazine)","retrieved":1714801033587},{"title":"One Chun","contents":"... that <b><a href=\"/wiki/One_Chun\" title=\"One Chun\">One Chun</a></b>, a <a href=\"/wiki/Michelin_Guide#Bib_Gourmand\" title=\"Michelin Guide\"><i>Michelin Guide</i> Bib Gourmand</a> restaurant, has <a href=\"/wiki/Black-and-white\" title=\"Black-and-white\">black-and-white</a> televisions, <a href=\"/wiki/Transistor_radio\" title=\"Transistor radio\">transistor radios</a>, and aged clocks on a wall?","link":"https://en.wikipedia.org/wiki/One_Chun","retrieved":1714801033588},{"title":"Heike Heubach","contents":"... that <b><a href=\"/wiki/Heike_Heubach\" title=\"Heike Heubach\">Heike Heubach</a></b> became the first deaf <a href=\"/wiki/Member_of_the_German_Bundestag\" title=\"Member of the German Bundestag\">member of the German Bundestag</a>?","link":"https://en.wikipedia.org/wiki/Heike_Heubach","retrieved":1714801033589},{"title":"Carabus japonicus","contents":"... that larvae of the species <i><b><a href=\"/wiki/Carabus_japonicus\" title=\"Carabus japonicus\">Carabus japonicus</a></b></i> prey on earthworms up to 400 times larger than themselves?","link":"https://en.wikipedia.org/wiki/Carabus_japonicus","retrieved":1714801033590},{"title":"Jonathan Elliot","contents":"... that <a href=\"/wiki/John_Quincy_Adams\" title=\"John Quincy Adams\">John Quincy Adams</a> described <b><a href=\"/wiki/Jonathan_Elliot_(publisher)\" title=\"Jonathan Elliot (publisher)\">Jonathan Elliot</a></b>, his former <a href=\"/wiki/Printer_(publishing)\" title=\"Printer (publishing)\">printer</a>, as \"penurious and venal\"?","link":"https://en.wikipedia.org/wiki/Jonathan_Elliot_(publisher)","retrieved":1714801033592},{"title":"Apocalypse Clown","contents":"... that an Irish comedy group wrote the film <i><b><a href=\"/wiki/Apocalypse_Clown\" title=\"Apocalypse Clown\">Apocalypse Clown</a></b></i><span style=\"padding-left:0.15em;\">?</span>","link":"https://en.wikipedia.org/wiki/Apocalypse_Clown","retrieved":1714801033593},{"title":"Anactoria","contents":"... that scholars debate whether <b><a href=\"/wiki/Anactoria\" title=\"Anactoria\">Anactoria</a></b>, mentioned in <a href=\"/wiki/Sappho\" title=\"Sappho\">Sappho</a>'s poems, was a real person, a <a href=\"/wiki/Pseudonym\" title=\"Pseudonym\">pseudonym</a>, or an invention of Sappho?","link":"https://en.wikipedia.org/wiki/Anactoria","retrieved":1714801033594},{"title":"American Colossus","contents":"... that <i><b><a href=\"/wiki/American_Colossus:_The_Triumph_of_Capitalism,_1865%E2%80%931900\" title=\"American Colossus: The Triumph of Capitalism, 1865–1900\">American Colossus</a></b></i>, a history book that describes how <a href=\"/wiki/J._P._Morgan\" title=\"J. P. Morgan\">a banker</a> bailed out the U.S. government in 1895, was published around <a href=\"/wiki/Great_Recession_in_the_United_States\" title=\"Great Recession in the United States\">a time when the U.S. government bailed out banks</a>?","link":"https://en.wikipedia.org/wiki/American_Colossus:_The_Triumph_of_Capitalism,_1865%E2%80%931900","retrieved":1714801033596},{"title":"Joe Gray","contents":"... that football player <b><a href=\"/wiki/Joe_Gray_(American_football)\" title=\"Joe Gray (American football)\">Joe Gray</a></b> was nicknamed the \"Gray Ghost\" because when running \"it was like he wasn't there anymore\"?","link":"https://en.wikipedia.org/wiki/Joe_Gray_(American_football)","retrieved":1714801033597}]}