{"title":"Wikipedia — did you know?","url":"https://en.wikipedia.org/wiki/Main_Page","favicon":"https://en.wikipedia.org/static/favicon/wikipedia.ico","elements":[{"title":"Edgar Matobato","contents":"... that ex-hitman <b><a href=\"/wiki/Edgar_Matobato\" title=\"Edgar Matobato\">Edgar Matobato</a></b> <i>(pictured)</i> fled the Philippines with a fake passport while posing as a gardener?","link":"https://en.wikipedia.org/wiki/Edgar_Matobato","retrieved":1749966235005},{"title":"Symphony in F major","contents":"... that <a href=\"/wiki/K%C5%8Dsaku_Yamada\" title=\"Kōsaku Yamada\">Yamada</a>'s <b><a href=\"/wiki/Symphony_in_F_major_(Yamada)\" title=\"Symphony in F major (Yamada)\">Symphony in F major</a></b> had to be reconstructed after a maritime accident and after the <a href=\"/wiki/Bombing_of_Tokyo\" title=\"Bombing of Tokyo\">bombing of Tokyo</a> during WWII?","link":"https://en.wikipedia.org/wiki/Symphony_in_F_major_(Yamada)","retrieved":1749966235006},{"title":"Chris Anderson","contents":"... that <b><a href=\"/wiki/Chris_Anderson_(golfer,_born_1961)\" title=\"Chris Anderson (golfer, born 1961)\">Chris Anderson</a></b> was one of three members of his family to win a <a href=\"/wiki/Delaware\" title=\"Delaware\">Delaware</a> state golf championship?","link":"https://en.wikipedia.org/wiki/Chris_Anderson_(golfer,_born_1961)","retrieved":1749966235008},{"title":"an episode of The Last of Us","contents":"... that a horse in <b><a href=\"/wiki/Day_One_(The_Last_of_Us)\" title=\"Day One (The Last of Us)\">an episode of <i>The Last of Us</i></a></b> previously appeared in <i><a href=\"/wiki/The_100_(TV_series)\" title=\"The 100 (TV series)\">The&nbsp;100</a></i> and <i><a href=\"/wiki/Jurassic_World_Dominion\" title=\"Jurassic World Dominion\">Jurassic World Dominion</a></i><span style=\"padding-left:0.15em;\">?</span>","link":"https://en.wikipedia.org/wiki/Day_One_(The_Last_of_Us)","retrieved":1749966235020},{"title":"Everyone Hates Elon","contents":"... that <b><a href=\"/wiki/Everyone_Hates_Elon\" title=\"Everyone Hates Elon\">Everyone Hates Elon</a></b> invited members of the public to destroy a <a href=\"/wiki/Tesla_Model_S\" title=\"Tesla Model S\">Tesla Model&nbsp;S</a> to raise money for food banks?","link":"https://en.wikipedia.org/wiki/Everyone_Hates_Elon","retrieved":1749966235021},{"title":"Chohan family murders","contents":"... that the 2004–2005 trial of the <b><a href=\"/wiki/Chohan_family_murders\" title=\"Chohan family murders\">Chohan family murders</a></b> was the longest in the history of the London <a href=\"/wiki/Metropolitan_Police\" title=\"Metropolitan Police\">Metropolitan Police</a>?","link":"https://en.wikipedia.org/wiki/Chohan_family_murders","retrieved":1749966235024},{"title":"Harriet","contents":"... that the meningitis storyline in the romance novel <i><b><a href=\"/wiki/Harriet_(novel)\" title=\"Harriet (novel)\">Harriet</a></b></i> was inspired by the illness of the author's son?","link":"https://en.wikipedia.org/wiki/Harriet_(novel)","retrieved":1749966235025},{"title":"2023 EFL League Two play-off final","contents":"... that the <b><a href=\"/wiki/2023_EFL_League_Two_play-off_final\" title=\"2023 EFL League Two play-off final\">2023 EFL League Two play-off final</a></b> saw a father–son duo on opposing coaching sides?","link":"https://en.wikipedia.org/wiki/2023_EFL_League_Two_play-off_final","retrieved":1749966235027},{"title":"a bird with huge feet","contents":"... that <b><a href=\"/wiki/Magnoavipes_denaliensis\" title=\"Magnoavipes denaliensis\">a bird with huge feet</a></b> once walked by a river near <a href=\"/wiki/Denali\" title=\"Denali\">Denali</a>?","link":"https://en.wikipedia.org/wiki/Magnoavipes_denaliensis","retrieved":1749966235029}]}