{"title":"Wikipedia — did you know?","url":"https://en.wikipedia.org/wiki/Main_Page","favicon":"https://en.wikipedia.org/static/favicon/wikipedia.ico","elements":[{"title":"Mosque of Ulmas al-Hajib","contents":"... that the <b><a href=\"/wiki/Mosque_of_Ulmas_al-Hajib\" title=\"Mosque of Ulmas al-Hajib\">Mosque of Ulmas al-Hajib</a></b> has the first \"flat\" <i><a href=\"/wiki/Muqarnas\" title=\"Muqarnas\">muqarnas</a></i> vault <i>(pictured)</i> in Cairo?","link":"https://en.wikipedia.org/wiki/Mosque_of_Ulmas_al-Hajib","retrieved":1710481038542},{"title":"Tidy Trax","contents":"... that the record label <b><a href=\"/wiki/Tidy_Trax\" title=\"Tidy Trax\">Tidy Trax</a></b> released an album in 2023 to commemorate the 25th anniversary of the death of  <a href=\"/wiki/Tony_De_Vit\" title=\"Tony De Vit\">Tony De Vit</a>, the \"godfather of <a href=\"/wiki/UK_hard_house\" title=\"UK hard house\">UK hard house</a>\"?","link":"https://en.wikipedia.org/wiki/Tidy_Trax","retrieved":1710481038544},{"title":"Bow Lake","contents":"... that the city of <a href=\"/wiki/Tacoma,_Washington\" title=\"Tacoma, Washington\">Tacoma, Washington</a>, incentivized building <a href=\"/wiki/Seattle%E2%80%93Tacoma_International_Airport\" title=\"Seattle–Tacoma International Airport\">Seattle–Tacoma International Airport</a> at <b><a href=\"/wiki/Bow_Lake_(SeaTac,_Washington)\" title=\"Bow Lake (SeaTac, Washington)\">Bow Lake</a></b> by contributing $100,000?","link":"https://en.wikipedia.org/wiki/Bow_Lake_(SeaTac,_Washington)","retrieved":1710481038546},{"title":"The Korea Daily News","contents":"... that after dodging censorship for years, <i><b><a href=\"/wiki/The_Korea_Daily_News\" title=\"The Korea Daily News\">The Korea Daily News</a></b></i> was finally bought out and turned into a publication of the <a href=\"/wiki/Korea_under_Japanese_rule\" title=\"Korea under Japanese rule\">Japanese colonial government in Korea</a>?","link":"https://en.wikipedia.org/wiki/The_Korea_Daily_News","retrieved":1710481038548},{"title":"Paula Arai","contents":"... that the <a href=\"/wiki/Buddhist_studies\" title=\"Buddhist studies\">Buddhist-studies</a> scholar <b><a href=\"/wiki/Paula_Arai\" title=\"Paula Arai\">Paula Arai</a></b> suffered racial and sexual discrimination while researching <a href=\"/wiki/S%C5%8Dt%C5%8D\" title=\"Sōtō\">Sōtō Zen</a> laywomen and nuns?","link":"https://en.wikipedia.org/wiki/Paula_Arai","retrieved":1710481038549},{"title":"Zwycięzcy oceanu","contents":"... that <i><b><a href=\"/wiki/Zwyci%C4%99zcy_oceanu\" title=\"Zwycięzcy oceanu\">Zwycięzcy oceanu</a></b></i>, a Polish young-adult adventure book from 1890, features Polish, English, and American characters?","link":"https://en.wikipedia.org/wiki/Zwyci%C4%99zcy_oceanu","retrieved":1710481038550},{"title":"Charles Knight","contents":"... that <b><a href=\"/wiki/Charles_Knight_(artist)\" title=\"Charles Knight (artist)\">Charles Knight</a></b><span class=\"nowrap\">'s</span> wartime painting activities led to him being mistaken for a German spy?","link":"https://en.wikipedia.org/wiki/Charles_Knight_(artist)","retrieved":1710481038552}]}