{"title":"Wikipedia — did you know?","url":"https://en.wikipedia.org/wiki/Main_Page","favicon":"https://en.wikipedia.org/static/favicon/wikipedia.ico","elements":[{"title":"Hôtel Albert Ciamberlani","contents":"... that the façade of <b><a href=\"/wiki/H%C3%B4tel_Albert_Ciamberlani\" title=\"Hôtel Albert Ciamberlani\">Hôtel Albert Ciamberlani</a></b> <i>(pictured)</i> has been described as one of the most beautiful <a href=\"/wiki/Art_Nouveau\" title=\"Art Nouveau\">Art Nouveau</a> façades in Belgium?","link":"https://en.wikipedia.org/wiki/H%C3%B4tel_Albert_Ciamberlani","retrieved":1677994649033},{"title":"Muchlis Ibrahim","contents":"... that <b><a href=\"/wiki/Muchlis_Ibrahim\" title=\"Muchlis Ibrahim\">Muchlis Ibrahim</a></b> opted to resign as governor when <b><a href=\"/wiki/Zainal_Bakar\" title=\"Zainal Bakar\">Zainal Bakar</a></b> was appointed to be his deputy instead of his choice?","link":"https://en.wikipedia.org/wiki/Muchlis_Ibrahim","retrieved":1677994649033},{"title":"a radio station in Illinois","contents":"... that even though an <a href=\"/wiki/Federal_Communications_Commission\" title=\"Federal Communications Commission\">FCC</a> examiner recommended denial of an application for <b><a href=\"/wiki/WNTA_(1150_AM)\" title=\"WNTA (1150 AM)\">a radio station in Illinois</a></b> after approving it twice, the commission granted it anyway?","link":"https://en.wikipedia.org/wiki/WNTA_(1150_AM)","retrieved":1677994649033},{"title":"Montagu Toller","contents":"... that <b><a href=\"/wiki/Montagu_Toller\" title=\"Montagu Toller\">Montagu Toller</a></b> was a part of the British team that played <a href=\"/wiki/Cricket_at_the_1900_Summer_Olympics\" title=\"Cricket at the 1900 Summer Olympics\">cricket at the 1900 Summer Olympics</a>, the only time cricket was ever featured at the Olympics?","link":"https://en.wikipedia.org/wiki/Montagu_Toller","retrieved":1677994649035},{"title":"Just Like a Woman","contents":"... that covers of <a href=\"/wiki/Bob_Dylan\" title=\"Bob Dylan\">Bob Dylan</a>'s \"<b><a href=\"/wiki/Just_Like_a_Woman\" title=\"Just Like a Woman\">Just Like a Woman</a></b>\" by <a href=\"/wiki/Manfred_Mann\" title=\"Manfred Mann\">Manfred Mann</a> and <a href=\"/wiki/Jonathan_King\" title=\"Jonathan King\">Jonathan King</a> were both coincidentally released on the same day Dylan was involved in a motorcycle accident?","link":"https://en.wikipedia.org/wiki/Just_Like_a_Woman","retrieved":1677994649041},{"title":"Cut Meutia","contents":"... that the <i><b><a href=\"/wiki/Cut_Meutia_(train)\" title=\"Cut Meutia (train)\">Cut Meutia</a></b></i> is the only active train service in Indonesia using <a href=\"/wiki/Standard-gauge_railway\" title=\"Standard-gauge railway\">standard-gauge track</a>?","link":"https://en.wikipedia.org/wiki/Cut_Meutia_(train)","retrieved":1677994649042},{"title":"School for American Crafts","contents":"... that the <b><a href=\"/wiki/School_for_American_Crafts\" title=\"School for American Crafts\">School for American Crafts</a></b> recruited faculty from Denmark to teach metalsmithing and woodworking?","link":"https://en.wikipedia.org/wiki/School_for_American_Crafts","retrieved":1677994649043},{"title":"31-day continuous livestream","contents":"... that <a href=\"/wiki/Ludwig_Ahgren\" title=\"Ludwig Ahgren\">Ludwig Ahgren</a> showered on camera during his <b><a href=\"/wiki/Ludwig%27s_subathon\" title=\"Ludwig's subathon\">31-day continuous livestream</a></b>?","link":"https://en.wikipedia.org/wiki/Ludwig%27s_subathon","retrieved":1677994649045}]}