{"title":"Wikipedia — did you know?","url":"https://en.wikipedia.org/wiki/Main_Page","favicon":"https://en.wikipedia.org/static/favicon/wikipedia.ico","elements":[{"title":"Johnny Gaudreau","contents":"... that <b><a href=\"/wiki/Johnny_Gaudreau\" title=\"Johnny Gaudreau\">Johnny Gaudreau</a></b> <i>(pictured)</i>, despite being one of the smallest players in the <a href=\"/wiki/National_Hockey_League\" title=\"National Hockey League\">National Hockey League</a>, was a seven-time <a href=\"/wiki/NHL_All-Star_Game\" title=\"NHL All-Star Game\">All-Star</a>?","link":"https://en.wikipedia.org/wiki/Johnny_Gaudreau","retrieved":1739252433367},{"title":"2022 Comhairle nan Eilean Siar election","contents":"... that Paul Steele was elected as council leader on the <a href=\"/wiki/Cut_(cards)#Drawing_lots\" title=\"Cut (cards)\">cut of a deck of cards</a> following the <b><a href=\"/wiki/2022_Comhairle_nan_Eilean_Siar_election\" title=\"2022 Comhairle nan Eilean Siar election\">2022 Comhairle nan Eilean Siar election</a></b>?","link":"https://en.wikipedia.org/wiki/2022_Comhairle_nan_Eilean_Siar_election","retrieved":1739252433369},{"title":"Santa Ynez Reservoir","contents":"... that the <b><a href=\"/wiki/Santa_Ynez_Reservoir\" title=\"Santa Ynez Reservoir\">Santa Ynez Reservoir</a></b> in <a href=\"/wiki/Pacific_Palisades,_Los_Angeles\" title=\"Pacific Palisades, Los Angeles\">Pacific Palisades</a>, which was built to provide water for firefighting, was empty when the 2025 <a href=\"/wiki/Palisades_Fire\" title=\"Palisades Fire\">Palisades Fire</a> began?","link":"https://en.wikipedia.org/wiki/Santa_Ynez_Reservoir","retrieved":1739252433370},{"title":"Wielka, większa i największa","contents":"... that Polish 1960 sci-fi novel <i><b><a href=\"/wiki/Wielka,_wi%C4%99ksza_i_najwi%C4%99ksza\" title=\"Wielka, większa i największa\">Wielka, większa i największa</a></b></i> was very influential for Polish young-adult literature?","link":"https://en.wikipedia.org/wiki/Wielka,_wi%C4%99ksza_i_najwi%C4%99ksza","retrieved":1739252433371},{"title":"Seek","contents":"... that the <a href=\"/wiki/Mass_in_the_Catholic_Church\" title=\"Mass in the Catholic Church\">Eucharistic liturgies</a> of <b><a href=\"/wiki/Seek_(conference)\" title=\"Seek (conference)\">Seek</a></b>, a Catholic young-adult conference which attracts thousands of attendees, are planned more than a year and a half in advance?","link":"https://en.wikipedia.org/wiki/Seek_(conference)","retrieved":1739252433372},{"title":"Humphrey III of Toron","contents":"... that in the early 1170s <b><a href=\"/wiki/Humphrey_III_of_Toron\" title=\"Humphrey III of Toron\">Humphrey&nbsp;III of Toron</a></b> may have been the lord of Transjordan, but he also may have been dead?","link":"https://en.wikipedia.org/wiki/Humphrey_III_of_Toron","retrieved":1739252433374},{"title":"Census Designated","contents":"... that <a href=\"/wiki/Jane_Remover\" title=\"Jane Remover\">Jane Remover</a> was inspired to create <i><b><a href=\"/wiki/Census_Designated\" title=\"Census Designated\">Census Designated</a></b></i> after a self-described \"near-death experience\" traveling through a blizzard?","link":"https://en.wikipedia.org/wiki/Census_Designated","retrieved":1739252433376},{"title":"Maria Einsmann","contents":"... that <b><a href=\"/wiki/Maria_Einsmann\" title=\"Maria Einsmann\">Maria Einsmann</a></b> claimed to be her own husband, Josef, when she registered the births of her companion Helene Müller's two children in 1921 and 1930?","link":"https://en.wikipedia.org/wiki/Maria_Einsmann","retrieved":1739252433378},{"title":"Death Angels","contents":"... that <b><a href=\"/wiki/Death_Angels_(A_Quiet_Place)\" title=\"Death Angels (A Quiet Place)\">Death Angels</a></b> are Happy?","link":"https://en.wikipedia.org/wiki/Death_Angels_(A_Quiet_Place)","retrieved":1739252433380}]}