{"title":"Wikipedia — did you know?","url":"https://en.wikipedia.org/wiki/Main_Page","favicon":"https://en.wikipedia.org/static/favicon/wikipedia.ico","elements":[{"title":"Cyprian Norwid","contents":"... that the 19th-century poet <b><a href=\"/wiki/Cyprian_Norwid\" title=\"Cyprian Norwid\">Cyprian Norwid</a></b> <i>(pictured)</i>, now recognized as one of the most important Polish poets, led a poverty-stricken life and his works were rarely appreciated until decades after his death?","link":"https://en.wikipedia.org/wiki/Cyprian_Norwid","retrieved":1695706643363},{"title":"Temple of Piety","contents":"... that ancient Rome's <b><a href=\"/wiki/Temple_of_Piety\" title=\"Temple of Piety\">Temple of Piety</a></b> was closely connected with the legend of a daughter who breastfed an imprisoned parent?","link":"https://en.wikipedia.org/wiki/Temple_of_Piety","retrieved":1695706643363},{"title":"Paul Needham","contents":"... that the librarian <b><a href=\"/wiki/Paul_Needham_(librarian)\" title=\"Paul Needham (librarian)\">Paul Needham</a></b> has argued for the \"respectful burial of the human remains\" included in a book bound in human skin?","link":"https://en.wikipedia.org/wiki/Paul_Needham_(librarian)","retrieved":1695706643363},{"title":"Solution and EU Party","contents":"... that the <b><a href=\"/wiki/Solution_and_EU_Party\" title=\"Solution and EU Party\">Solution and EU Party</a></b> aimed to represent 30 percent of <a href=\"/wiki/Northern_Cyprus\" title=\"Northern Cyprus\">Turkish Cypriots</a>, but failed to enter the <a href=\"/wiki/Assembly_of_the_Republic_(Northern_Cyprus)\" title=\"Assembly of the Republic (Northern Cyprus)\">Northern Cypriot parliament</a>?","link":"https://en.wikipedia.org/wiki/Solution_and_EU_Party","retrieved":1695706643364},{"title":"their 2020 season","contents":"... that <a href=\"/wiki/Seattle_Sounders_FC\" title=\"Seattle Sounders FC\">Seattle Sounders FC</a> players held their practices over <a href=\"/wiki/Zoom_(software)\" title=\"Zoom (software)\">Zoom</a> during part of <b><a href=\"/wiki/2020_Seattle_Sounders_FC_season\" title=\"2020 Seattle Sounders FC season\">their 2020 season</a></b>?","link":"https://en.wikipedia.org/wiki/2020_Seattle_Sounders_FC_season","retrieved":1695706643365},{"title":"No Saint","contents":"... that according to <i>Rolling Stone</i>, <a href=\"/wiki/Lauren_Jenkins\" title=\"Lauren Jenkins\">Lauren Jenkins</a> blended music and acting for <i><b><a href=\"/wiki/No_Saint\" title=\"No Saint\">No Saint</a></b></i> \"in ways not currently common practice\" in country music?","link":"https://en.wikipedia.org/wiki/No_Saint","retrieved":1695706643368},{"title":"Thorfinn","contents":"... that <b><a href=\"/wiki/Thorfinn_(Vinland_Saga)\" title=\"Thorfinn (Vinland Saga)\">Thorfinn</a></b><span class=\"nowrap\">'s</span> journey to <a href=\"/wiki/Vinland\" title=\"Vinland\">Vinland</a> in the manga <i><a href=\"/wiki/Vinland_Saga_(manga)\" title=\"Vinland Saga (manga)\">Vinland Saga</a></i> was influenced by the author's anxieties during the <a href=\"/wiki/Cold_War\" title=\"Cold War\">Cold War</a> and the <a href=\"/wiki/September_11_attacks\" title=\"September 11 attacks\">September&nbsp;11 attacks</a>?","link":"https://en.wikipedia.org/wiki/Thorfinn_(Vinland_Saga)","retrieved":1695706643371},{"title":"bicolor molly","contents":"... that the <b><a href=\"/wiki/Poecilia_catemaconis\" title=\"Poecilia catemaconis\">bicolor molly</a></b> inevitably goes off the deep end in adulthood?","link":"https://en.wikipedia.org/wiki/Poecilia_catemaconis","retrieved":1695706643375}]}