{"title":"Wikipedia — did you know?","url":"https://en.wikipedia.org/wiki/Main_Page","favicon":"https://en.wikipedia.org/static/favicon/wikipedia.ico","elements":[{"title":"Zénith","contents":"... that the two victims of the <i><b><a href=\"/wiki/Z%C3%A9nith_(balloon)\" title=\"Zénith (balloon)\">Zénith</a></b></i> balloon incident are depicted holding hands on their tomb <i>(pictured)</i><span style=\"padding-left:0.15em;\">?</span>","link":"https://en.wikipedia.org/wiki/Z%C3%A9nith_(balloon)","retrieved":1724045898380},{"title":"Lionel Haward","contents":"... that <b><a href=\"/wiki/Lionel_Haward\" title=\"Lionel Haward\">Lionel Haward</a></b> applied an early example of <a href=\"/wiki/Offender_profiling\" title=\"Offender profiling\">offender profiling</a> to help identify high-ranking Nazis disguised as ordinary troops?","link":"https://en.wikipedia.org/wiki/Lionel_Haward","retrieved":1724045898381},{"title":"Until Then","contents":"... that the adventure game <i><b><a href=\"/wiki/Until_Then\" title=\"Until Then\">Until Then</a></b></i> has an in-universe version of Facebook where the player can like and comment on other characters' posts?","link":"https://en.wikipedia.org/wiki/Until_Then","retrieved":1724045898382},{"title":"Lisa M. Corrigan","contents":"... that <b><a href=\"/wiki/Lisa_M._Corrigan\" title=\"Lisa M. Corrigan\">Lisa M. Corrigan</a></b> used the prison memoirs of black activists to show how incarceration impacted the <a href=\"/wiki/Black_power_movement\" title=\"Black power movement\">black power movement</a>?","link":"https://en.wikipedia.org/wiki/Lisa_M._Corrigan","retrieved":1724045898383},{"title":"a shipwreck in the eastern Mediterranean","contents":"... that <b><a href=\"/wiki/Canaanite_shipwreck\" title=\"Canaanite shipwreck\">a shipwreck in the eastern Mediterranean</a></b>, dating from the Late Bronze Age, is the earliest deep-sea shipwreck to be discovered?","link":"https://en.wikipedia.org/wiki/Canaanite_shipwreck","retrieved":1724045898384},{"title":"Johann Joseph Dömling","contents":"... that <b><a href=\"/wiki/Johann_Joseph_D%C3%B6mling\" title=\"Johann Joseph Dömling\">Johann Joseph Dömling</a></b> suggested in 1803 that <a href=\"/wiki/Venous_blood\" title=\"Venous blood\">venous blood</a> contained <a href=\"/wiki/Carbon_monoxide\" title=\"Carbon monoxide\">carbon monoxide</a>?","link":"https://en.wikipedia.org/wiki/Johann_Joseph_D%C3%B6mling","retrieved":1724045898385},{"title":"Togo's abortion law","contents":"... that <b><a href=\"/wiki/Abortion_in_Togo\" title=\"Abortion in Togo\">Togo's abortion law</a></b> was one of the first in Africa to allow abortion in the case of rape?","link":"https://en.wikipedia.org/wiki/Abortion_in_Togo","retrieved":1724045898387},{"title":"Dissolution Grip","contents":"... that <i><b><a href=\"/wiki/Dissolution_Grip\" title=\"Dissolution Grip\">Dissolution Grip</a></b></i> by <b><a href=\"/wiki/KMRU\" title=\"KMRU\">KMRU</a></b> uses recordings of the artist's shack being struck by strong winds?","link":"https://en.wikipedia.org/wiki/Dissolution_Grip","retrieved":1724045898389},{"title":"headless priest","contents":"... that, according to a local myth, a <b><a href=\"/wiki/Headless_priest\" title=\"Headless priest\">headless priest</a></b> cursed <a href=\"/wiki/Le%C3%B3n_Viejo\" title=\"León Viejo\">León Viejo</a> with earthquakes?","link":"https://en.wikipedia.org/wiki/Headless_priest","retrieved":1724045898390}]}